LICENSE
README.md
pyproject.toml
setup.cfg
setup.py
buildurl/__init__.py
buildurl/builder.py
buildurl/py.typed
buildurl.egg-info/PKG-INFO
buildurl.egg-info/SOURCES.txt
buildurl.egg-info/dependency_links.txt
buildurl.egg-info/not-zip-safe
buildurl.egg-info/top_level.txt
tests/__init__.py
tests/test_buildurl.py