Metadata-Version: 2.1
Name: buildurl
Version: 4.0.1
Summary: Simple URL builder
Home-page: https://github.com/MicaelJarniac/BuildURL
Author: Micael Jarniac
Author-email: micael@jarniac.dev
License: MIT
Project-URL: Bug Tracker, https://github.com/MicaelJarniac/BuildURL/issues
Platform: UNKNOWN
Classifier: Programming Language :: Python :: 3
Classifier: Programming Language :: Python :: 3 :: Only
Classifier: License :: OSI Approved :: MIT License
Classifier: Operating System :: OS Independent
Requires-Python: >=3.6
License-File: LICENSE
